psr1983_mymath_package/__init__.py
psr1983_mymath_package/add.py
psr1983_mymath_package/subtract.py
psr1983_mymath_package/misc/__init__.py
psr1983_mymath_package/misc/divide.py
psr1983_mymath_package/misc/multiply.py
psr1983_mymath_package-1.0.dist-info/METADATA
psr1983_mymath_package-1.0.dist-info/WHEEL
psr1983_mymath_package-1.0.dist-info/top_level.txt
psr1983_mymath_package-1.0.dist-info/RECORD
